{
    "layers": {
        "learjet_position": {
            "id":       "learjet_position",
            "title":    "LearJet position",
            "subtitle": "latitude / longitude",
            "tags":     "location",
            "group":    "overlays",
            "format":       "image/png",
            "period":       "subdaily",
            "startDate":    "2018-07-01",
            "endDate":      "2021-01-01",
            "type":         "wmts",

            "projections": {
                "geographic": {
                    "matrixSet":    "EPSG4326_500m",
                    "source":       "GIBS:geographic"
                }
            }
        }
    }
}
